memory.v

`timescale 1ns/1ns

 module Memory
   #(parameter ADDR_WIDTH = 32,
     parameter DATA_WIDTH = 32,
     parameter DEPTH = (2*32)-1)
    (
     input [ADDR_WIDTH-1:0] ADDR,
     input CS,CLK,
     input RE,
     input [DATA_WIDTH-1:0] WR_MEM_DATA,
     output reg[DATA_WIDTH-1:0] RE_MEM_DATA
     );

  
   reg [DATA_WIDTH-1:0] mem[0:DEPTH];

   parameter init_file_select = 0;
    	
     initial
         begin
	 if(init_file_select ==1)
               $readmemh("input.txt",mem,0,((2*32)-1));
         else if(init_file_select == 2)
	       $readmemh("mem_y.txt",mem,0,((2*32)-1));
         end
   
     always @(posedge CLK) begin
	     if(CS)
		     if(RE) begin
			     RE_MEM_DATA <= mem[ADDR];
		     end
		     else if(RE == 1'b0) begin
			     mem[ADDR] <= WR_MEM_DATA;
		     end
	     end

 endmodule

alu.v
 
 `timescale 1ns/1ns

  module alu #(parameter DATA_WIDTH =32, CONTROL =4)(

   input [DATA_WIDTH-1:0]in,in3,

   input [CONTROL-1:0]opcode,

   output [DATA_WIDTH-1:0]alu_out,

  //input Enable,

   output parity_flag,
          zero_flag,
	      sign_flag,
          carry_flag,
	      auxillary_flag
          );

//    localparam DATA_WIDTH = 32, CONTROL = 4;

   wire [DATA_WIDTH-1:0] adder_sub_out,logic_operation_out,bitwise_operation_out,shift_operation_out;

                                              //   opcode[1:0] = 00  +  opcode[2]                         // 0/1 (ADDITION/SUBTRACTION) -> 1-BIT   
					      //   opcode[1:0] = 01  +  opcode[3:2]			  // 00/01/10/11 (Logical Operation) --> 2-BIT
					      //   opcode[1:0] = 10  +  opcode[3:2]			  // 00/01/10/11 (bitwise Operation) --> 2-BIT
					      //   opcode[1:0] = 11  +  opcode[3:2]			  // 00/01/10/11 (shift Operation) --> 2-BIT

  assign parity_flag = ~^alu_out ;
  assign zero_flag = (alu_out == 0) ;
  assign sign_flag = alu_out[DATA_WIDTH-1] ;

  assign alu_out = (opcode[1:0] == 0) ? adder_sub_out : 
		   ((opcode[1:0] == 2'd1) ? logic_operation_out : 
		   ((opcode[1:0] == 2'd2) ? bitwise_operation_out: 
	           ((opcode[1:0] == 2'd3) ? shift_operation_out : in))) ;



   adder_sub a1(                                   // ADDITION AND SUBTRACTION Operation
	      in,in3,
	      opcode[2],
	      adder_sub_out,
	      carry_flag,
	      auxillary_flag 
	      );
		                                          
                                                  

   logic_operation a2(
	              in,in3,
	             opcode[3:2],                  // AND,OR,NOT,logical equality
	              logic_operation_out 
	             );

   bitwise_operation a3(
	              in,in3,
	              opcode[3:2],                  // bitwise- (AND,OR,NOT,xor)
	               bitwise_operation_out
	               );

   shift_operation a4(
	             in,in3,
	             opcode[3:2],                  // shift- (right,left,arithmetic left,arithmetic right)
	             shift_operation_out
	             );


 endmodule  


     module adder_sub #(parameter DATA_WIDTH = 32)(                                   // ADDITION AND SUBTRACTION Operation
	   input [DATA_WIDTH-1:0]in1,in4,
	   input opcode,
	   output [DATA_WIDTH-1:0]add_sum,
	   output carry_flag,
	   output auxillary_carry 
	   );
	   
           wire [DATA_WIDTH-1:0]temp;

           adder_sub_16 we1(in1[15:0],in4[15:0],opcode,1'b0,add_sum[15:0],auxillary_carry);
           adder_sub_16 we2(in1[31:16],in4[31:16],opcode,auxillary_carry,add_sum[31:16],carry_flag);

	  endmodule

      module adder_sub_16 #(parameter DATA_WIDTH =32)(                                   // ADDITION AND SUBTRACTION Operation
	   input [((DATA_WIDTH/2)-1):0]in5,in6,
	   input opcode,cin,
	   output [((DATA_WIDTH/2)-1):0]add_sum,
	   output carry
	   );
	  // localparam DATA_WIDTH = 32; 
           wire [(DATA_WIDTH/2):0]temp;
        
       	  //assign temp = {(DATA_WIDTH/2){opcode}} ^ {in2,cin};                                        // 2's complement logic

          //  assign {auxillary_carry,add_sum[15:0]} = in1[15:0] + temp[15:0] + opcode;       // if opcode = 1 SUB else ADD operation
     
	  // assign {carry,add_sum} = in1 + temp + opcode ;
	 
	  assign {carry,add_sum} = opcode ? (in5-in6-cin) : (in5+in6+cin) ;

	  endmodule



  module logic_operation #(parameter DATA_WIDTH =32)(
	   input [DATA_WIDTH-1:0]a,b,
	   input [1:0]opcode,                  // AND,OR,NOT,logical equality
	   output [DATA_WIDTH-1:0]out 
	   );
    
 //localparam DATA_WIDTH = 32; 

	   assign out = (opcode == 0) ? a&&b : 
		          ((opcode==2'd1) ? (a||b) : 
		     	  ((opcode==2'd2) ? !a : 
			      ((opcode==2'd3) ? (a==b) : a))) ;

		endmodule

   module bitwise_operation #(parameter DATA_WIDTH =32) (
	   input [DATA_WIDTH-1:0]c,d,
	   input [1:0]opcode,                  // bitwise- (AND,OR,NOT,xor)
	   output [DATA_WIDTH-1:0]out 
	   );
    
 //localparam DATA_WIDTH = 32; 

	   assign out = (opcode == 0) ? c&d : 
		        ((opcode==2'd1) ? (c|d) : 
			     ((opcode==2'd2) ? ~c : 
			    ((opcode==2'd3) ? (c^d) : c ))) ;

		endmodule


   module shift_operation #(parameter DATA_WIDTH =32) (
	   input [DATA_WIDTH-1:0]e,f,
	   input [1:0]opcode,                  // shift- (right,left,arithmetic left,arithmetic right)
	   output [DATA_WIDTH-1:0]out 
	   );
   //localparam DATA_WIDTH = 32; 


	   assign out = (opcode == 0) ? e>>f : 
		        ((opcode==2'd1) ? (e<<f) : 
			((opcode==2'd2) ? e<<<f : 
			((opcode==2'd3) ? (e>>>f) : e))) ;

		endmodule

regbank.v
  module regbank(RE_A, RE_B, RE_X, WD, MEM_WD, SRA, SRB, DR, W_INST, R_INST, CLK);
    
	 input CLK;
	 input [5:0] SRA, SRB,W_INST,R_INST, DR;   //source and destination reg
	 input [31:0] WD, MEM_WD;            // write data
	 output [31:0] RE_X,RE_A, RE_B;    //read data 
	
	
	 reg [31:0] regfile [0:63];  //array of registers
	initial
         begin
          $readmemh("mem.txt",regfile,0,63);
         end
	 
	 assign RE_A = regfile[SRA];
	 assign RE_B = regfile[SRB];
	 assign RE_X = regfile[R_INST];

	 
	 always @(posedge CLK)
		         begin regfile [DR] <= WD; 
                               regfile[W_INST] <= MEM_WD;
			 end
	    	   
  endmodule

top.v


  `include "alu.v"
  `include "regbank.v"
  `include "memory.v"




 `timescale 1ns/1ns


  module top  #(parameter DATA_WIDTH = 32)(
	    input [DATA_WIDTH-1:0]A_imm,B_imm,ADDR,
	    input [1:0]sel,
	    input CLK,
	    input [21:0]OSD,
	    input X,Y,R_W,
            input [5:0]W_INST,R_INST,
	    output parity_flag,zero_flag,sign_flag,carry_flag,auxillary_flag,
	    output reg [DATA_WIDTH-1:0]Result
            );

	  
	   wire [DATA_WIDTH-1:0]alu_out,A_reg,B_reg,A,B,RE_MEM,WR_MEM,RE_MEM_REG,RE_MEM_X, RE_MEM_Y;
	   reg [5:0]source_A,source_B,des;
	   reg [3:0]opcode;
           reg [DATA_WIDTH-1:0]A_imm_reg,B_imm_reg,ADDR_reg;
	   reg [1:0]reg_sel;
	   reg [5:0]W_INST_reg,R_INST_reg;
	   reg X_reg,Y_reg,CS_X_reg,CS_Y_reg,WE_X_reg,WE_Y_reg,RE_X_reg,RE_Y_reg;
	  

         
	 assign  {A,B} = (reg_sel[1:0] == 2'd0) ?  {A_reg,B_reg} : 
		             ((reg_sel[1:0] == 2'd1) ? {A_reg,B_imm_reg} : 
		             ((reg_sel[1:0] == 2'd2) ? {A_imm_reg,B_reg} : 
                             ((reg_sel[1:0] == 2'd3) ? {A_imm_reg,B_imm_reg} : {A,B}))) ;

  
     regbank reg_bank(A_reg, B_reg, WR_MEM, alu_out ,
	              RE_MEM_REG, source_A, source_B, des,W_INST_reg, R_INST_reg, CLK);


     alu alu_block(A,B,opcode,alu_out,parity_flag,zero_flag,sign_flag,carry_flag,auxillary_flag);  

     Memory #(.init_file_select(1)) X1(ADDR_reg, CS_X_reg, CLK, RE_X_reg, WR_MEM, RE_MEM_X);

     Memory #(.init_file_select(1)) X2(ADDR_reg, CS_X_reg, CLK, WE_X_reg, WR_MEM, RE_MEM);

     Memory #(.init_file_select(2)) Y1(ADDR_reg, CS_Y_reg, CLK, RE_Y_reg, WR_MEM, RE_MEM_Y);

     Memory #(.init_file_select(2)) Y2(ADDR_reg, CS_Y_reg, CLK, WE_Y_reg, WR_MEM, RE_MEM);
    
     
  
   assign RE_MEM_REG = CS_X_reg ? RE_MEM_X : RE_MEM_Y ;

     always @(posedge CLK)
	     	begin
			A_imm_reg <= A_imm;
			B_imm_reg <= B_imm;
		    {opcode,source_A,source_B,des} <= OSD;
			Result <= alu_out;
			reg_sel <= sel;
			W_INST_reg <= W_INST;
			R_INST_reg <= R_INST;
                        ADDR_reg <= ADDR;
			if(X_reg) begin
				CS_X_reg <= 1'b1;
			        if(R_W)
				  RE_X_reg <= 1'b1;
			        else if(!R_W)
				  WE_X_reg <= 1'b0; end
			else if(Y_reg) begin
				CS_Y_reg <= 1'b1;
				if(R_W)
				  RE_Y_reg <= 1'b1;
			        else if(!R_W)
				  WE_Y_reg <= 1'b0; end

			else
			begin
				CS_X_reg <= 1'b0;
				CS_Y_reg <= 1'b0;
			end
		           
		
			{X_reg,Y_reg} <= {X,Y};
		  //  {write_X_reg,write_Y_reg} <= {write_X,write_Y};
	       	end

  endmodule

testnew.v
`timescale 1ns/1ns

  module test_top;
      parameter DATA_WIDTH = 32;
            reg [DATA_WIDTH-1:0]A_imm, B_imm, ADDR;
	    reg [1:0]sel;
	    reg CLK;
            reg X,Y,R_W;
            reg [5:0]W_INST,R_INST;
            
	    reg [21:0]OSD;
	    wire parity_flag,zero_flag,sign_flag,carry_flag,auxillary_flag;
	    wire [DATA_WIDTH-1:0]Result;

	   
  integer i, file,file2,file3;
  
  top  t1(A_imm,B_imm,ADDR,
	    sel,
	     CLK,
	     OSD,
	     X,Y,R_W,
             W_INST,R_INST,
	     parity_flag,zero_flag,sign_flag,carry_flag,auxillary_flag,
	     Result
             );


  reg enable =0;


  initial begin
   CLK=0;
   forever #5 CLK = ~CLK ;
  end
    reg [31:0]buffer[0:63];
		
       initial
	begin
	 $readmemh ("TVector.txt", buffer,0,63);
       end

       initial
	begin
	file = $fopen("ALUOperationResult.txt"); //blank file
        file2 = $fopen("LOADResult.txt"); //blank file
	file3 = $fopen("STOREResult.txt"); //blank file
        end


  integer k,p,j;
  initial
  begin

  //************ Reading data from X1 and storing at regbank**************//
    
         for (k = 0; k<=63; k = k+1)
		 begin
                  X = 1; Y=0; R_W= 1;
                  W_INST = k;
		  ADDR = k;
		  @(negedge CLK); #20;
                  if(t1.X1.mem[ADDR] == t1.reg_bank.regfile[W_INST])
		     begin 
                           $fwrite (file2,"matched in vector\n",);
	             @(negedge CLK); end
                  else
	             begin
		           $fwrite (file2,$time,"  :%d: mismatched in vector %h\n",k,t1.X1.mem[ADDR]);
	             @(negedge CLK); end
              //  OSD[5:0] = ADDR;
                 end
             $fwrite(file2,"*******************************END OF OPERATION*********************************");

         
  //************ ALU ADD Operation taking previous X1 data as a A number and B Immediate number**************//
         for (j = 0; j<=63; j = j+1)
           begin
                OSD[21:18]=4'D0;  OSD[17:12]=j; B_imm= 32'd43; sel=2'd1;  // adding values in ALU
                 @(negedge CLK)  OSD[5:0]=j;  
		 @(negedge CLK); 
	        
		 if (Result == buffer[j])
	             begin $display ("matched in vector %h", buffer[j]);
		     $fwrite (file, "matched in vector %h\n", buffer[j]); 
		           
	             @(negedge CLK); end
                 else
	             begin $display ("%d: mismatched in vector %h != %h",j, buffer[j],Result);
		            $fwrite (file,"%d: mismatched in vector %h != %h\n",j, buffer[j],Result);

	             @(negedge CLK); end
           end
             $fwrite(file,"\n*******************************END OF OPERATION*********************************");

  //************ Writing Regbank data in Memory Y2**************//
          for (p = 0; p<=63; p = p+1)
           begin
	      @(negedge CLK);
              X=0; Y=1;  R_W=0; R_INST = p; 
	      @(negedge CLK); #15;
	       if(t1.Y2.mem[ADDR] == t1.reg_bank.regfile[R_INST])
		     begin 
                           $fwrite (file3,$time," :matched in vector %h\n", t1.reg_bank.regfile[R_INST]);
	             @(negedge CLK); end
                  else
	             begin
		           $fwrite (file3,$time,"  :%d: mismatched in vector %h != %h\n",k,t1.Y2.mem[ADDR], t1.reg_bank.regfile[R_INST]);
	             @(negedge CLK); end
      
                 end
                     $fwrite(file3,"*******************************END OF OPERATION*********************************");

        repeat(2) @(negedge CLK); 
          #10	$finish;
        end
	

	
	

	
	initial
	begin
	#2500 $fdisplay(file); 
	end
	
	initial
	#5000 $fclose(file); 
	
	
	
  initial begin
   $dumpfile("topWave.vcd");
   $dumpvars;
  end
 
  endmodule

topWave.vcd
$date
	Wed Jul 14 00:29:34 2021
$end
$version
	Icarus Verilog
$end
$timescale
	1ns
$end
$scope module test_top $end
$var wire 1 ! zero_flag $end
$var wire 1 " sign_flag $end
$var wire 1 # parity_flag $end
$var wire 1 $ carry_flag $end
$var wire 1 % auxillary_flag $end
$var wire 32 & Result [31:0] $end
$var reg 32 ' ADDR [31:0] $end
$var reg 32 ( A_imm [31:0] $end
$var reg 32 ) B_imm [31:0] $end
$var reg 1 * CLK $end
$var reg 22 + OSD [21:0] $end
$var reg 6 , R_INST [5:0] $end
$var reg 1 - R_W $end
$var reg 6 . W_INST [5:0] $end
$var reg 1 / X $end
$var reg 1 0 Y $end
$var reg 1 1 enable $end
$var reg 2 2 sel [1:0] $end
$var integer 32 3 file [31:0] $end
$var integer 32 4 file2 [31:0] $end
$var integer 32 5 file3 [31:0] $end
$var integer 32 6 j [31:0] $end
$var integer 32 7 k [31:0] $end
$var integer 32 8 p [31:0] $end
$scope module t1 $end
$var wire 32 9 ADDR [31:0] $end
$var wire 32 : A_imm [31:0] $end
$var wire 32 ; B_imm [31:0] $end
$var wire 1 * CLK $end
$var wire 22 < OSD [21:0] $end
$var wire 32 = RE_MEM [31:0] $end
$var wire 6 > R_INST [5:0] $end
$var wire 1 - R_W $end
$var wire 6 ? W_INST [5:0] $end
$var wire 1 / X $end
$var wire 1 0 Y $end
$var wire 2 @ sel [1:0] $end
$var wire 1 ! zero_flag $end
$var wire 1 " sign_flag $end
$var wire 1 # parity_flag $end
$var wire 1 $ carry_flag $end
$var wire 1 % auxillary_flag $end
$var wire 32 A alu_out [31:0] $end
$var wire 32 B WR_MEM [31:0] $end
$var wire 32 C RE_MEM_Y [31:0] $end
$var wire 32 D RE_MEM_X [31:0] $end
$var wire 32 E RE_MEM_REG [31:0] $end
$var wire 32 F B_reg [31:0] $end
$var wire 32 G B [31:0] $end
$var wire 32 H A_reg [31:0] $end
$var wire 32 I A [31:0] $end
$var reg 32 J ADDR_reg [31:0] $end
$var reg 32 K A_imm_reg [31:0] $end
$var reg 32 L B_imm_reg [31:0] $end
$var reg 1 M CS_X_reg $end
$var reg 1 N CS_Y_reg $end
$var reg 1 O RE_X_reg $end
$var reg 1 P RE_Y_reg $end
$var reg 6 Q R_INST_reg [5:0] $end
$var reg 32 R Result [31:0] $end
$var reg 1 S WE_X_reg $end
$var reg 1 T WE_Y_reg $end
$var reg 6 U W_INST_reg [5:0] $end
$var reg 1 V X_reg $end
$var reg 1 W Y_reg $end
$var reg 6 X des [5:0] $end
$var reg 4 Y opcode [3:0] $end
$var reg 2 Z reg_sel [1:0] $end
$var reg 6 [ source_A [5:0] $end
$var reg 6 \ source_B [5:0] $end
$scope module X1 $end
$var wire 32 ] ADDR [31:0] $end
$var wire 1 * CLK $end
$var wire 1 M CS $end
$var wire 1 O RE $end
$var wire 32 ^ WR_MEM_DATA [31:0] $end
$var reg 32 _ RE_MEM_DATA [31:0] $end
$upscope $end
$scope module X2 $end
$var wire 32 ` ADDR [31:0] $end
$var wire 1 * CLK $end
$var wire 1 M CS $end
$var wire 1 S RE $end
$var wire 32 a WR_MEM_DATA [31:0] $end
$var reg 32 b RE_MEM_DATA [31:0] $end
$upscope $end
$scope module Y1 $end
$var wire 32 c ADDR [31:0] $end
$var wire 1 * CLK $end
$var wire 1 N CS $end
$var wire 1 P RE $end
$var wire 32 d WR_MEM_DATA [31:0] $end
$var reg 32 e RE_MEM_DATA [31:0] $end
$upscope $end
$scope module Y2 $end
$var wire 32 f ADDR [31:0] $end
$var wire 1 * CLK $end
$var wire 1 N CS $end
$var wire 1 T RE $end
$var wire 32 g WR_MEM_DATA [31:0] $end
$var reg 32 h RE_MEM_DATA [31:0] $end
$upscope $end
$scope module alu_block $end
$var wire 32 i in [31:0] $end
$var wire 32 j in3 [31:0] $end
$var wire 4 k opcode [3:0] $end
$var wire 1 ! zero_flag $end
$var wire 1 " sign_flag $end
$var wire 32 l shift_operation_out [31:0] $end
$var wire 1 # parity_flag $end
$var wire 32 m logic_operation_out [31:0] $end
$var wire 1 $ carry_flag $end
$var wire 32 n bitwise_operation_out [31:0] $end
$var wire 1 % auxillary_flag $end
$var wire 32 o alu_out [31:0] $end
$var wire 32 p adder_sub_out [31:0] $end
$scope module a1 $end
$var wire 32 q in1 [31:0] $end
$var wire 32 r in4 [31:0] $end
$var wire 1 s opcode $end
$var wire 1 $ carry_flag $end
$var wire 1 % auxillary_carry $end
$var wire 32 t add_sum [31:0] $end
$scope module we1 $end
$var wire 1 u cin $end
$var wire 16 v in5 [15:0] $end
$var wire 16 w in6 [15:0] $end
$var wire 1 s opcode $end
$var wire 1 % carry $end
$var wire 16 x add_sum [15:0] $end
$upscope $end
$scope module we2 $end
$var wire 1 % cin $end
$var wire 16 y in5 [15:0] $end
$var wire 16 z in6 [15:0] $end
$var wire 1 s opcode $end
$var wire 1 $ carry $end
$var wire 16 { add_sum [15:0] $end
$upscope $end
$upscope $end
$scope module a2 $end
$var wire 32 | a [31:0] $end
$var wire 32 } b [31:0] $end
$var wire 2 ~ opcode [1:0] $end
$var wire 32 !" out [31:0] $end
$upscope $end
$scope module a3 $end
$var wire 32 "" c [31:0] $end
$var wire 32 #" d [31:0] $end
$var wire 2 $" opcode [1:0] $end
$var wire 32 %" out [31:0] $end
$upscope $end
$scope module a4 $end
$var wire 32 &" e [31:0] $end
$var wire 32 '" f [31:0] $end
$var wire 2 (" opcode [1:0] $end
$var wire 32 )" out [31:0] $end
$upscope $end
$upscope $end
$scope module reg_bank $end
$var wire 1 * CLK $end
$var wire 6 *" DR [5:0] $end
$var wire 32 +" MEM_WD [31:0] $end
$var wire 32 ," RE_A [31:0] $end
$var wire 32 -" RE_B [31:0] $end
$var wire 32 ." RE_X [31:0] $end
$var wire 6 /" R_INST [5:0] $end
$var wire 6 0" SRA [5:0] $end
$var wire 6 1" SRB [5:0] $end
$var wire 32 2" WD [31:0] $end
$var wire 6 3" W_INST [5:0] $end
$upscope $end
$upscope $end
$upscope $end
$enddefinitions $end
#0
$dumpvars
bx 3"
bx 2"
bx 1"
bx 0"
bx /"
bx ."
bx -"
bx ,"
bx +"
bx *"
bx )"
bx ("
bx '"
bx &"
bx %"
bx $"
bx #"
bx ""
bx !"
bx ~
bx }
bx |
bx {
bx z
bx y
bx x
bx w
bx v
0u
bx t
xs
bx r
bx q
bx p
bx o
bx n
bx m
bx l
bx k
bx j
bx i
bx h
bx g
bx f
bx e
bx d
bx c
bx b
bx a
bx `
bx _
bx ^
bx ]
bx \
bx [
bx Z
bx Y
bx X
xW
xV
bx U
xT
xS
bx R
bx Q
xP
xO
xN
xM
bx L
bx K
bx J
bx I
bx H
bx G
bx F
bx E
bx D
bx C
bx B
bx A
bx @
b0 ?
bx >
bx =
bx <
bx ;
bx :
b0 9
bx 8
b0 7
bx 6
b1000 5
b100 4
b10 3
bx 2
01
00
1/
b0 .
1-
bx ,
bx +
0*
bx )
bx (
b0 '
bx &
x%
x$
x#
x"
x!
$end
#5
1V
0W
0N
0M
b0 J
b0 ]
b0 `
b0 c
b0 f
b0 U
b0 3"
1*
#10
0*
#15
1O
1M
1*
#20
0*
#25
b11001001001101111111000100110 E
b11001001001101111111000100110 +"
b11001001001101111111000100110 D
b11001001001101111111000100110 _
1*
#30
b1 '
b1 9
b1 .
b1 ?
b1 7
0*
#35
b1 J
b1 ]
b1 `
b1 c
b1 f
b1 U
b1 3"
1*
#40
0*
#45
b11101001101001011011001101011 E
b11101001101001011011001101011 +"
b11101001101001011011001101011 D
b11101001101001011011001101011 _
1*
#50
0*
#55
1*
#60
b10 '
b10 9
b10 .
b10 ?
b10 7
0*
#65
b10 J
b10 ]
b10 `
b10 c
b10 f
b10 U
b10 3"
1*
#70
0*
#75
b1110100101011010010010111111 E
b1110100101011010010010111111 +"
b1110100101011010010010111111 D
b1110100101011010010010111111 _
1*
#80
0*
#85
1*
#90
b11 '
b11 9
b11 .
b11 ?
b11 7
0*
#95
b11 J
b11 ]
b11 `
b11 c
b11 f
b11 U
b11 3"
1*
#100
0*
#105
b1010001111111101100001111000 E
b1010001111111101100001111000 +"
b1010001111111101100001111000 D
b1010001111111101100001111000 _
1*
#110
0*
#115
1*
#120
b100 '
b100 9
b100 .
b100 ?
b100 7
0*
#125
b100 J
b100 ]
b100 `
b100 c
b100 f
b100 U
b100 3"
1*
#130
0*
#135
b11000110001000101011000000100 E
b11000110001000101011000000100 +"
b11000110001000101011000000100 D
b11000110001000101011000000100 _
1*
#140
0*
#145
1*
#150
b101 '
b101 9
b101 .
b101 ?
b101 7
0*
#155
b101 J
b101 ]
b101 `
b101 c
b101 f
b101 U
b101 3"
1*
#160
0*
#165
b100110101010000010011001000101 E
b100110101010000010011001000101 +"
b100110101010000010011001000101 D
b100110101010000010011001000101 _
1*
#170
0*
#175
1*
#180
b110 '
b110 9
b110 .
b110 ?
b110 7
0*
#185
b110 J
b110 ]
b110 `
b110 c
b110 f
b110 U
b110 3"
1*
#190
0*
#195
b11100100110111000000100101010 E
b11100100110111000000100101010 +"
b11100100110111000000100101010 D
b11100100110111000000100101010 _
1*
#200
0*
#205
1*
#210
b111 '
b111 9
b111 .
b111 ?
b111 7
0*
#215
b111 J
b111 ]
b111 `
b111 c
b111 f
b111 U
b111 3"
1*
#220
0*
#225
b101001100100101011001111000000 E
b101001100100101011001111000000 +"
b101001100100101011001111000000 D
b101001100100101011001111000000 _
1*
#230
0*
#235
1*
#240
b1000 '
b1000 9
b1000 .
b1000 ?
b1000 7
0*
#245
b1000 J
b1000 ]
b1000 `
b1000 c
b1000 f
b1000 U
b1000 3"
1*
#250
0*
#255
b101011100110001001010101000100 E
b101011100110001001010101000100 +"
b101011100110001001010101000100 D
b101011100110001001010101000100 _
1*
#260
0*
#265
1*
#270
b1001 '
b1001 9
b1001 .
b1001 ?
b1001 7
0*
#275
b1001 J
b1001 ]
b1001 `
b1001 c
b1001 f
b1001 U
b1001 3"
1*
#280
0*
#285
b101000100000111111110110000100 E
b101000100000111111110110000100 +"
b101000100000111111110110000100 D
b101000100000111111110110000100 _
1*
#290
0*
#295
1*
#300
b1010 '
b1010 9
b1010 .
b1010 ?
b1010 7
0*
#305
b1010 J
b1010 ]
b1010 `
b1010 c
b1010 f
b1010 U
b1010 3"
1*
#310
0*
#315
b100000000101111000000011011011 E
b100000000101111000000011011011 +"
b100000000101111000000011011011 D
b100000000101111000000011011011 _
1*
#320
0*
#325
1*
#330
b1011 '
b1011 9
b1011 .
b1011 ?
b1011 7
0*
#335
b1011 J
b1011 ]
b1011 `
b1011 c
b1011 f
b1011 U
b1011 3"
1*
#340
0*
#345
b110110000111011011111101110010 E
b110110000111011011111101110010 +"
b110110000111011011111101110010 D
b110110000111011011111101110010 _
1*
#350
0*
#355
1*
#360
b1100 '
b1100 9
b1100 .
b1100 ?
b1100 7
0*
#365
b1100 J
b1100 ]
b1100 `
b1100 c
b1100 f
b1100 U
b1100 3"
1*
#370
0*
#375
b10000110100110001111110 E
b10000110100110001111110 +"
b10000110100110001111110 D
b10000110100110001111110 _
1*
#380
0*
#385
1*
#390
b1101 '
b1101 9
b1101 .
b1101 ?
b1101 7
0*
#395
b1101 J
b1101 ]
b1101 `
b1101 c
b1101 f
b1101 U
b1101 3"
1*
#400
0*
#405
b11001011010110101100001110000 E
b11001011010110101100001110000 +"
b11001011010110101100001110000 D
b11001011010110101100001110000 _
1*
#410
0*
#415
1*
#420
b1110 '
b1110 9
b1110 .
b1110 ?
b1110 7
0*
#425
b1110 J
b1110 ]
b1110 `
b1110 c
b1110 f
b1110 U
b1110 3"
1*
#430
0*
#435
b110101110111011000000001100111 E
b110101110111011000000001100111 +"
b110101110111011000000001100111 D
b110101110111011000000001100111 _
1*
#440
0*
#445
1*
#450
b1111 '
b1111 9
b1111 .
b1111 ?
b1111 7
0*
#455
b1111 J
b1111 ]
b1111 `
b1111 c
b1111 f
b1111 U
b1111 3"
1*
#460
0*
#465
b1110010111010100011000001011 E
b1110010111010100011000001011 +"
b1110010111010100011000001011 D
b1110010111010100011000001011 _
1*
#470
0*
#475
1*
#480
b10000 '
b10000 9
b10000 .
b10000 ?
b10000 7
0*
#485
b10000 J
b10000 ]
b10000 `
b10000 c
b10000 f
b10000 U
b10000 3"
1*
#490
0*
#495
b11110011101011001010100011001 E
b11110011101011001010100011001 +"
b11110011101011001010100011001 D
b11110011101011001010100011001 _
1*
#500
0*
#505
1*
#510
b10001 '
b10001 9
b10001 .
b10001 ?
b10001 7
0*
#515
b10001 J
b10001 ]
b10001 `
b10001 c
b10001 f
b10001 U
b10001 3"
1*
#520
0*
#525
b11011001110100010011110011110 E
b11011001110100010011110011110 +"
b11011001110100010011110011110 D
b11011001110100010011110011110 _
1*
#530
0*
#535
1*
#540
b10010 '
b10010 9
b10010 .
b10010 ?
b10010 7
0*
#545
b10010 J
b10010 ]
b10010 `
b10010 c
b10010 f
b10010 U
b10010 3"
1*
#550
0*
#555
b100000001110111001100110111001 E
b100000001110111001100110111001 +"
b100000001110111001100110111001 D
b100000001110111001100110111001 _
1*
#560
0*
#565
1*
#570
b10011 '
b10011 9
b10011 .
b10011 ?
b10011 7
0*
#575
b10011 J
b10011 ]
b10011 `
b10011 c
b10011 f
b10011 U
b10011 3"
1*
#580
0*
#585
b101011011010001011011011000 E
b101011011010001011011011000 +"
b101011011010001011011011000 D
b101011011010001011011011000 _
1*
#590
0*
#595
1*
#600
b10100 '
b10100 9
b10100 .
b10100 ?
b10100 7
0*
#605
b10100 J
b10100 ]
b10100 `
b10100 c
b10100 f
b10100 U
b10100 3"
1*
#610
0*
#615
b100001100100010000101001110100 E
b100001100100010000101001110100 +"
b100001100100010000101001110100 D
b100001100100010000101001110100 _
1*
#620
0*
#625
1*
#630
b10101 '
b10101 9
b10101 .
b10101 ?
b10101 7
0*
#635
b10101 J
b10101 ]
b10101 `
b10101 c
b10101 f
b10101 U
b10101 3"
1*
#640
0*
#645
b1111001010001011100100001 E
b1111001010001011100100001 +"
b1111001010001011100100001 D
b1111001010001011100100001 _
1*
#650
0*
#655
1*
#660
b10110 '
b10110 9
b10110 .
b10110 ?
b10110 7
0*
#665
b10110 J
b10110 ]
b10110 `
b10110 c
b10110 f
b10110 U
b10110 3"
1*
#670
0*
#675
b1010000101010111100001100011 E
b1010000101010111100001100011 +"
b1010000101010111100001100011 D
b1010000101010111100001100011 _
1*
#680
0*
#685
1*
#690
b10111 '
b10111 9
b10111 .
b10111 ?
b10111 7
0*
#695
b10111 J
b10111 ]
b10111 `
b10111 c
b10111 f
b10111 U
b10111 3"
1*
#700
0*
#705
b100110001000010011011000111100 E
b100110001000010011011000111100 +"
b100110001000010011011000111100 D
b100110001000010011011000111100 _
1*
#710
0*
#715
1*
#720
b11000 '
b11000 9
b11000 .
b11000 ?
b11000 7
0*
#725
b11000 J
b11000 ]
b11000 `
b11000 c
b11000 f
b11000 U
b11000 3"
1*
#730
0*
#735
b11100011000110110101100010001 E
b11100011000110110101100010001 +"
b11100011000110110101100010001 D
b11100011000110110101100010001 _
1*
#740
0*
#745
1*
#750
b11001 '
b11001 9
b11001 .
b11001 ?
b11001 7
0*
#755
b11001 J
b11001 ]
b11001 `
b11001 c
b11001 f
b11001 U
b11001 3"
1*
#760
0*
#765
b1101111010001001100010111001 E
b1101111010001001100010111001 +"
b1101111010001001100010111001 D
b1101111010001001100010111001 _
1*
#770
0*
#775
1*
#780
b11010 '
b11010 9
b11010 .
b11010 ?
b11010 7
0*
#785
b11010 J
b11010 ]
b11010 `
b11010 c
b11010 f
b11010 U
b11010 3"
1*
#790
0*
#795
b110111000000001011111110011101 E
b110111000000001011111110011101 +"
b110111000000001011111110011101 D
b110111000000001011111110011101 _
1*
#800
0*
#805
1*
#810
b11011 '
b11011 9
b11011 .
b11011 ?
b11011 7
0*
#815
b11011 J
b11011 ]
b11011 `
b11011 c
b11011 f
b11011 U
b11011 3"
1*
#820
0*
#825
b11001001011100010111101100010 E
b11001001011100010111101100010 +"
b11001001011100010111101100010 D
b11001001011100010111101100010 _
1*
#830
0*
#835
1*
#840
b11100 '
b11100 9
b11100 .
b11100 ?
b11100 7
0*
#845
b11100 J
b11100 ]
b11100 `
b11100 c
b11100 f
b11100 U
b11100 3"
1*
#850
0*
#855
b110111000011111000111011101010 E
b110111000011111000111011101010 +"
b110111000011111000111011101010 D
b110111000011111000111011101010 _
1*
#860
0*
#865
1*
#870
b11101 '
b11101 9
b11101 .
b11101 ?
b11101 7
0*
#875
b11101 J
b11101 ]
b11101 `
b11101 c
b11101 f
b11101 U
b11101 3"
1*
#880
0*
#885
b11111000010000110011001010101 E
b11111000010000110011001010101 +"
b11111000010000110011001010101 D
b11111000010000110011001010101 _
1*
#890
0*
#895
1*
#900
b11110 '
b11110 9
b11110 .
b11110 ?
b11110 7
0*
#905
b11110 J
b11110 ]
b11110 `
b11110 c
b11110 f
b11110 U
b11110 3"
1*
#910
0*
#915
b100000110010000100101110101011 E
b100000110010000100101110101011 +"
b100000110010000100101110101011 D
b100000110010000100101110101011 _
1*
#920
0*
#925
1*
